clii/__init__.py
clii/clii.py
clii/py.typed
tests/test_misc.py
clii-1.0.3.dist-info/LICENSE
clii-1.0.3.dist-info/METADATA
clii-1.0.3.dist-info/WHEEL
clii-1.0.3.dist-info/top_level.txt
clii-1.0.3.dist-info/RECORD
