Metadata-Version: 2.1
Name: clii
Version: 1.0.3
Summary: Python functions -> CLI
Author-email: James O'Beirne <w.clii@au92.org>
Project-URL: Homepage, https://github.com/jamesob/clii
Project-URL: Bug Tracker, https://github.com/jamesob/clii/issues
Requires-Python: >=3.7
License-File: LICENSE
